gitlab_jobs_exporter/__init__.py
gitlab_jobs_exporter-0.2.0.data/scripts/gitlab_jobs_exporter
gitlab_jobs_exporter-0.2.0.dist-info/LICENSE
gitlab_jobs_exporter-0.2.0.dist-info/METADATA
gitlab_jobs_exporter-0.2.0.dist-info/WHEEL
gitlab_jobs_exporter-0.2.0.dist-info/top_level.txt
gitlab_jobs_exporter-0.2.0.dist-info/RECORD
