Metadata-Version: 2.1
Name: gitlab-jobs-exporter
Version: 0.2.0
Summary: prometheus exporter for exporting job metrics in a project
Home-page: https://github.com/xinau/gitlab_jobs_exporter
Author: Felix Ehrenpfort
Author-email: felix.ehrenpfort@protonmail.com
License: MIT
Platform: UNKNOWN
Requires-Dist: prometheus-client
Requires-Dist: python-dateutil
